anipy_cli/__init__.py
anipy_cli/anilist_proxy.py
anipy_cli/arg_parser.py
anipy_cli/cli.py
anipy_cli/clis/__init__.py
anipy_cli/clis/anilist_cli.py
anipy_cli/clis/base_cli.py
anipy_cli/clis/binge_cli.py
anipy_cli/clis/default_cli.py
anipy_cli/clis/download_cli.py
anipy_cli/clis/history_cli.py
anipy_cli/clis/mal_cli.py
anipy_cli/clis/seasonal_cli.py
anipy_cli/colors.py
anipy_cli/config.py
anipy_cli/discord.py
anipy_cli/download_component.py
anipy_cli/logger.py
anipy_cli/mal_proxy.py
anipy_cli/menus/__init__.py
anipy_cli/menus/anilist_menu.py
anipy_cli/menus/base_menu.py
anipy_cli/menus/mal_menu.py
anipy_cli/menus/menu.py
anipy_cli/menus/seasonal_menu.py
anipy_cli/prompts.py
anipy_cli/util.py
anipy_cli-3.8.3.dist-info/METADATA
anipy_cli-3.8.3.dist-info/WHEEL
anipy_cli-3.8.3.dist-info/entry_points.txt
anipy_cli-3.8.3.dist-info/RECORD
