Metadata-Version: 2.4
Name: anipy-cli
Version: 3.8.3
Summary: Watch and Download anime from the comfort of your Terminal
License: GPL-3.0
Keywords: anime,cli
Author: sdaqo
Author-email: sdaqo.dev@protonmail.com
Requires-Python: >=3.10,<4.0
Classifier: License :: OSI Approved :: GNU General Public License v3 (GPLv3)
Classifier: Programming Language :: Python :: 3
Classifier: Programming Language :: Python :: 3.10
Classifier: Programming Language :: Python :: 3.11
Classifier: Programming Language :: Python :: 3.12
Classifier: Programming Language :: Python :: 3.13
Classifier: Programming Language :: Python :: 3.14
Requires-Dist: anipy-api (>=3.8.3,<4.0.0)
Requires-Dist: appdirs (>=1.4.4,<2.0.0)
Requires-Dist: inquirerpy (>=0.3.4,<0.4.0)
Requires-Dist: pypresence (>=4.3.0,<5.0.0)
Requires-Dist: pyyaml (>=6.0.1,<7.0.0)
Requires-Dist: yaspin (>=3.0.2,<4.0.0)
Project-URL: Bug Tracker, https://github.com/sdaqo/anipy-cli/issues
Project-URL: Documentation, https://sdaqo.github.io/anipy-cli/getting-started-cli
Project-URL: Homepage, https://sdaqo.github.io/anipy-cli
Project-URL: Repository, https://github.com/sdaqo/anipy-cli
